whoid/__init__.py
whoid/auth.py
whoid_api-0.0.5.dist-info/METADATA
whoid_api-0.0.5.dist-info/WHEEL
whoid_api-0.0.5.dist-info/top_level.txt
whoid_api-0.0.5.dist-info/RECORD
