Metadata-Version: 2.1
Name: whoid-api
Version: 0.0.5
Summary: API for whoid.ru
Home-page: https://github.com/sl1pperq/whoid-api
Author: sl1pper
Author-email: averin_sd@icloud.com
Project-URL: GitHub, https://github.com/sl1pperq/whoid-api
Keywords: id 1561 auth
Classifier: Programming Language :: Python :: 3.11
Classifier: License :: OSI Approved :: MIT License
Classifier: Operating System :: OS Independent
Requires-Python: >=3.6
Requires-Dist: requests
Requires-Dist: pytelegrambotapi
